avlset/__init__.py
avlset/avlset.py
avlset-0.1.0.dist-info/LICENSE
avlset-0.1.0.dist-info/METADATA
avlset-0.1.0.dist-info/WHEEL
avlset-0.1.0.dist-info/top_level.txt
avlset-0.1.0.dist-info/RECORD
