Metadata-Version: 2.1
Name: avlset
Version: 0.1.0
Summary: An AVL tree set implementation in Python.
Author: Gabe Rust
Author-email: gabe@rekt.run
License-File: LICENSE
